tickersnap/__init__.py
tickersnap/py.typed
tickersnap/lists/__init__.py
tickersnap/lists/api.py
tickersnap/lists/asset.py
tickersnap/lists/models.py
tickersnap/mmi/__init__.py
tickersnap/mmi/api.py
tickersnap/mmi/mmi.py
tickersnap/mmi/models.py
tickersnap/stock/__init__.py
tickersnap/stock/api.py
tickersnap/stock/models.py
tickersnap/stock/scorecard.py
tickersnap-0.0.4.dist-info/licenses/LICENSE
tickersnap-0.0.4.dist-info/METADATA
tickersnap-0.0.4.dist-info/WHEEL
tickersnap-0.0.4.dist-info/top_level.txt
tickersnap-0.0.4.dist-info/RECORD
