Metadata-Version: 2.4
Name: tickersnap
Version: 0.0.4
Summary: Tickersnap is a tool for getting snapshots of stock data from www.tickertape.in
Author-email: Atanu Sarkar <mratanusarkar@gmail.com>
Maintainer-email: Atanu Sarkar <mratanusarkar@gmail.com>
License-Expression: Apache-2.0
Project-URL: Homepage, https://github.com/mratanusarkar/tickersnap
Project-URL: Documentation, https://mratanusarkar.github.io/tickersnap
Project-URL: Repository, https://github.com/mratanusarkar/tickersnap
Project-URL: Bug Tracker, https://github.com/mratanusarkar/tickersnap/issues
Project-URL: Changelog, https://github.com/mratanusarkar/tickersnap/releases
Keywords: finance,stock,market,data,financial,analysis,automation,sentiment,screening,tickertape
Classifier: Development Status :: 3 - Alpha
Classifier: Intended Audience :: Developers
Classifier: Intended Audience :: End Users/Desktop
Classifier: Intended Audience :: Financial and Insurance Industry
Classifier: Operating System :: OS Independent
Classifier: Programming Language :: Python :: 3
Classifier: Programming Language :: Python :: 3.10
Classifier: Programming Language :: Python :: 3.11
Classifier: Programming Language :: Python :: 3.12
Classifier: Programming Language :: Python :: 3.13
Classifier: Topic :: Office/Business :: Financial
Classifier: Topic :: Office/Business :: Financial :: Investment
Classifier: Topic :: Software Development :: Libraries :: Python Modules
Requires-Python: >=3.10
License-File: LICENSE
Requires-Dist: pydantic>=2.0.0
Requires-Dist: httpx>=0.25.0
Requires-Dist: tqdm>=4.67.1
Provides-Extra: dev
Requires-Dist: pip>=24.2; extra == "dev"
Requires-Dist: uv>=0.4.20; extra == "dev"
Requires-Dist: pytest>=8.3.3; extra == "dev"
Requires-Dist: isort>=5.13.2; extra == "dev"
Requires-Dist: black>=24.10.0; extra == "dev"
Requires-Dist: ruff>=0.6.9; extra == "dev"
Provides-Extra: docs
Requires-Dist: mkdocs>=1.6.1; extra == "docs"
Requires-Dist: mkdocstrings>=0.26.1; extra == "docs"
Requires-Dist: mkdocstrings-python>=1.11.1; extra == "docs"
Requires-Dist: mkdocs-material>=9.5.39; extra == "docs"
Requires-Dist: mkdocs-minify-plugin>=0.8.0; extra == "docs"
Requires-Dist: mkdocs-glightbox>=0.4.0; extra == "docs"
Requires-Dist: mkdocs-jupyter>=0.25.0; extra == "docs"
Requires-Dist: jupyter>=1.1.1; extra == "docs"
Dynamic: license-file
